[
    {
      "productName": "4K Ultra HD Smart TV",
      "productImage": "https://i.ibb.co/mvfBBr6/pexels-fotios-photos-1444416.jpg",
      "description": "A 55-inch 4K Ultra HD Smart TV with HDR and voice control.",
      "price": 699.99,
      "category": "Electronics",
      "brandName": "VisionTech",
      "rating": 4.7,
      "creationDateTime": "2024-08-01T10:00:00Z"
    },
    {
      "productName": "Wireless Noise-Cancelling Headphones",
      "productImage": "https://i.ibb.co/mvfBBr6/pexels-fotios-photos-1444416.jpghttps://i.ibb.co/Tt5sfmy/pexels-garrettmorrow-1649771.jpg",
      "description": "Premium wireless headphones with active noise cancellation.",
      "price": 199.99,
      "category": "Electronics",
      "brandName": "VisionTech",
      "rating": 4.8,
      "creationDateTime": "2024-07-31T12:30:00Z"
    },
    {
      "productName": "Smart Home Security Camera",
      "productImage": "https://i.ibb.co/ZgHTjN3/pexels-hikaique-243757.jpg",
      "description": "A smart home security camera with night vision and motion detection.",
      "price": 149.99,
      "category": "Home",
      "brandName": "VisionTech",
      "rating": 4.6,
      "creationDateTime": "2024-07-30T09:15:00Z"
    },
    {
      "productName": "Bluetooth Speaker",
      "productImage": "https://i.ibb.co/X3jXqBt/pexels-khang-20802448.jpg",
      "description": "A portable Bluetooth speaker with deep bass and 12-hour battery life.",
      "price": 79.99,
      "category": "Electronics",
      "brandName": "VisionTech",
      "rating": 4.5,
      "creationDateTime": "2024-07-29T11:45:00Z"
    },
    {
      "productName": "Smart Thermostat",
      "productImage": "https://i.ibb.co/nkpSpwc/pexels-introspectivedsgn-7616651.jpg",
      "description": "A smart thermostat with energy-saving features and app control.",
      "price": 129.99,
      "category": "Home",
      "brandName": "VisionTech",
      "rating": 4.7,
      "creationDateTime": "2024-07-28T13:30:00Z"
    },
    {
      "productName": "Treadmill",
      "productImage": "https://i.ibb.co/Zc8ZnLG/pexels-willpicturethis-1954524.jpg",
      "description": "A high-performance treadmill with multiple workout programs.",
      "price": 899.99,
      "category": "Sportswear",
      "brandName": "FitGear",
      "rating": 4.8,
      "creationDateTime": "2024-07-27T15:00:00Z"
    },
    {
      "productName": "Yoga Mat",
      "productImage": "https://i.ibb.co/VxJWs65/pexels-823sl-2294363.jpg",
      "description": "A non-slip yoga mat with extra thickness for comfort.",
      "price": 29.99,
      "category": "Sportswear",
      "brandName": "FitGear",
      "rating": 4.6,
      "creationDateTime": "2024-07-26T10:20:00Z"
    },
    {
      "productName": "Running Shoes",
      "productImage": "https://i.ibb.co/C8ckZr5/pexels-pixabay-163535.jpg",
      "description": "Lightweight running shoes with breathable mesh and cushioned sole.",
      "price": 79.99,
      "category": "Sportswear",
      "brandName": "FitGear",
      "rating": 4.7,
      "creationDateTime": "2024-07-25T11:10:00Z"
    },
    {
      "productName": "Fitness Tracker",
      "productImage": "https://i.ibb.co/zZSn3B3/pexels-tdcat-437036.jpg",
      "description": "A fitness tracker with heart rate monitor and GPS.",
      "price": 99.99,
      "category": "Sportswear",
      "brandName": "FitGear",
      "rating": 4.8,
      "creationDateTime": "2024-07-24T12:00:00Z"
    },
    {
      "productName": "Dumbbell Set",
      "productImage": "https://i.ibb.co/NFwRWKJ/pexels-karolina-grabowska-4397841.jpg",
      "description": "A set of adjustable dumbbells with a storage rack.",
      "price": 129.99,
      "category": "Sportswear",
      "brandName": "FitGear",
      "rating": 4.7,
      "creationDateTime": "2024-07-23T13:30:00Z"
    },
    {
      "productName": "Electric Toothbrush",
      "productImage": "https://i.ibb.co/2svDRLW/pexels-karolina-grabowska-4202938.jpg",
      "description": "A rechargeable electric toothbrush with multiple modes.",
      "price": 79.99,
      "category": "Beauty & Health",
      "brandName": "WellnessPro",
      "rating": 4.6,
      "creationDateTime": "2024-07-22T09:55:00Z"
    },
    {
      "productName": "Hair Dryer",
      "productImage": "https://i.ibb.co/PwgFB4R/pexels-element5-973402.jpg",
      "description": "A powerful hair dryer with ionic technology.",
      "price": 49.99,
      "category": "Beauty & Health",
      "brandName": "WellnessPro",
      "rating": 4.8,
      "creationDateTime": "2024-07-21T11:00:00Z"
    },
    {
      "productName": "Electric Shaver",
      "productImage": "https://i.ibb.co/q040FYv/pexels-mostafameraji-3037244.jpg",
      "description": "A wet and dry electric shaver with precision blades.",
      "price": 129.99,
      "category": "Beauty & Health",
      "brandName": "WellnessPro",
      "rating": 4.5,
      "creationDateTime": "2024-07-20T13:50:00Z"
    },
    {
      "productName": "Facial Steamer",
      "productImage": "https://i.ibb.co/zHSXfsx/pexels-shvetsa-5069494.jpg",
      "description": "A portable facial steamer for deep cleansing and hydration.",
      "price": 39.99,
      "category": "Beauty & Health",
      "brandName": "WellnessPro",
      "rating": 4.6,
      "creationDateTime": "2024-07-19T08:55:00Z"
    },
    {
      "productName": "Massage Gun",
      "productImage": "https://i.ibb.co/nmrJ6xw/pexels-tima-miroshnichenko-6388978.jpg",
      "description": "A handheld deep tissue massage gun with multiple attachments.",
      "price": 99.99,
      "category": "Beauty & Health",
      "brandName": "WellnessPro",
      "rating": 4.7,
      "creationDateTime": "2024-07-18T12:25:00Z"
    },
    {
      "productName": "Men's Slim Fit Jeans",
      "productImage": "https://i.ibb.co/G7hgZXt/pexels-allan-mas-5369441.jpg",
      "description": "A pair of slim-fit jeans with stretch for comfort.",
      "price": 49.99,
      "category": "Fashion",
      "brandName": "StyleIcon",
      "rating": 4.5,
      "creationDateTime": "2024-07-17T14:00:00Z"
    },
    {
      "productName": "Women's Summer Dress",
      "productImage": "https://i.ibb.co/W3zQkvg/pexels-majesticaljasmin-17392875.jpg",
      "description": "A lightweight summer dress with floral prints.",
      "price": 39.99,
      "category": "Fashion",
      "brandName": "StyleIcon",
      "rating": 4.6,
      "creationDateTime": "2024-07-16T16:10:00Z"
    },
    {
      "productName": "Leather Jacket",
      "productImage": "https://i.ibb.co/NZpmsRN/pexels-dnsfotos-2569465.jpg",
      "description": "A stylish leather jacket with a slim-fit design.",
      "price": 199.99,
      "category": "Fashion",
      "brandName": "StyleIcon",
      "rating": 4.8,
      "creationDateTime": "2024-07-15T17:45:00Z"
    },
    {
      "productName": "Sneakers",
      "productImage": "https://i.ibb.co/dP1zDNb/pexels-nytheone-1070360.jpg",
      "description": "A pair of trendy sneakers with cushioned soles.",
      "price": 79.99,
      "category": "Fashion",
      "brandName": "StyleIcon",
      "rating": 4.7,
      "creationDateTime": "2024-07-14T11:20:00Z"
    },
    {
      "productName": "Men's Formal Shirt",
      "productImage": "https://i.ibb.co/K505pJ5/pexels-pro5-vn-1368185933-26336890.jpg",
      "description": "A classic men's formal shirt with a modern fit.",
      "price": 29.99,
      "category": "Fashion",
      "brandName": "StyleIcon",
      "rating": 4.5,
      "creationDateTime": "2024-07-13T09:40:00Z"
    },
    {
      "productName": "Men's Sunglasses",
      "productImage": "https://i.ibb.co/KwNQHkx/pexels-photography-maghradze-ph-1659410-25961108.jpg",
      "description": "A pair of polarized men's sunglasses with UV protection.",
      "price": 59.99,
      "category": "Fashion",
      "brandName": "SunGuard",
      "rating": 4.8,
      "creationDateTime": "2024-07-12T10:35:00Z"
    },
    {
      "productName": "Women's Sunglasses",
      "productImage": "https://i.ibb.co/34vJ1yM/pexels-nam-day-1382824483-26125808.jpg",
      "description": "A pair of stylish women's sunglasses with UV protection.",
      "price": 69.99,
      "category": "Fashion",
      "brandName": "SunGuard",
      "rating": 4.7,
      "creationDateTime": "2024-07-11T12:20:00Z"
    },
    {
      "productName": "Sports Watch",
      "productImage": "https://i.ibb.co/hR0249N/pexels-pixabay-158741.jpg",
      "description": "A durable sports watch with water resistance and GPS.",
      "price": 149.99,
      "category": "Electronics",
      "brandName": "VisionTech",
      "rating": 4.7,
      "creationDateTime": "2024-07-10T14:15:00Z"
    },
    {
      "productName": "Laptop Backpack",
      "productImage": "https://i.ibb.co/0XSVGwf/pexels-armin-rimoldi-5553124.jpg",
      "description": "A laptop backpack with multiple compartments and USB charging port.",
      "price": 49.99,
      "category": "Home",
      "brandName": "VisionTech",
      "rating": 4.6,
      "creationDateTime": "2024-07-09T09:25:00Z"
    },
    {
      "productName": "Smartphone",
      "productImage": "https://i.ibb.co/6F5M6xv/pexels-george-dolgikh-551816-1310532.jpg",
      "description": "A latest-gen smartphone with a stunning display and powerful processor.",
      "price": 999.99,
      "category": "Electronics",
      "brandName": "VisionTech",
      "rating": 4.8,
      "creationDateTime": "2024-07-08T11:10:00Z"
    },
    {
      "productName": "Wireless Earbuds",
      "productImage": "https://i.ibb.co/X46n0DH/pexels-cup-of-couple-6177556.jpg",
      "description": "True wireless earbuds with noise cancellation and long battery life.",
      "price": 129.99,
      "category": "Electronics",
      "brandName": "VisionTech",
      "rating": 4.7,
      "creationDateTime": "2024-07-07T13:00:00Z"
    },
    {
      "productName": "Smartwatch",
      "productImage": "https://i.ibb.co/T4YSy0v/pexels-ingo-1682821.jpg",
      "description": "A smartwatch with fitness tracking, notifications, and heart rate monitor.",
      "price": 199.99,
      "category": "Electronics",
      "brandName": "VisionTech",
      "rating": 4.6,
      "creationDateTime": "2024-07-06T15:30:00Z"
    },
    {
      "productName": "Robot Vacuum Cleaner",
      "productImage": "https://i.ibb.co/F4kQKSd/pexels-cottonbro-4112723.jpg",
      "description": "A smart robot vacuum cleaner with app control and auto-charging.",
      "price": 299.99,
      "category": "Home",
      "brandName": "VisionTech",
      "rating": 4.7,
      "creationDateTime": "2024-07-05T10:40:00Z"
    },
    {
      "productName": "Air Purifier",
      "productImage": "https://i.ibb.co/tsNc0PJ/pexels-dbaler-10127241.jpg",
      "description": "An air purifier with HEPA filter and real-time air quality monitoring.",
      "price": 149.99,
      "category": "Home",
      "brandName": "VisionTech",
      "rating": 4.6,
      "creationDateTime": "2024-07-04T09:15:00Z"
    },
    {
      "productName": "Blender",
      "productImage": "https://i.ibb.co/FH83tsP/pexels-yaroslav-shuraev-8845082.jpg",
      "description": "A high-speed blender with multiple speed settings and pulse function.",
      "price": 99.99,
      "category": "Home",
      "brandName": "VisionTech",
      "rating": 4.7,
      "creationDateTime": "2024-07-03T08:55:00Z"
    },
    {
      "productName": "Coffee Maker",
      "productImage": "https://i.ibb.co/4fP9fkY/pexels-karine-monteiro-1132429-2147683.jpg",
      "description": "A drip coffee maker with programmable settings and 12-cup capacity.",
      "price": 89.99,
      "category": "Home",
      "brandName": "VisionTech",
      "rating": 4.5,
      "creationDateTime": "2024-07-02T11:20:00Z"
    },
    {
      "productName": "Toaster Oven",
      "productImage": "https://i.ibb.co/HP0KkXQ/pexels-zvolskiy-2062426.jpg",
      "description": "A versatile toaster oven with convection cooking and multiple functions.",
      "price": 79.99,
      "category": "Home",
      "brandName": "VisionTech",
      "rating": 4.6,
      "creationDateTime": "2024-07-01T10:10:00Z"
    },
    {
      "productName": "Smart Light Bulbs",
      "productImage": "https://i.ibb.co/VBKsc8c/pexels-ian-panelo-7425353.jpg",
      "description": "A set of smart light bulbs with app control and color-changing features.",
      "price": 49.99,
      "category": "Home",
      "brandName": "VisionTech",
      "rating": 4.7,
      "creationDateTime": "2024-06-30T12:00:00Z"
    },
    {
      "productName": "Running Tights",
      "productImage": "https://i.ibb.co/TkByYfW/pexels-rdne-7187836.jpg",
      "description": "Comfortable running tights with moisture-wicking fabric.",
      "price": 39.99,
      "category": "Sportswear",
      "brandName": "FitGear",
      "rating": 4.6,
      "creationDateTime": "2024-06-29T09:50:00Z"
    },
    {
      "productName": "Sports Bra",
      "productImage": "https://i.ibb.co/JychJMT/pexels-rethaferguson-3061217.jpg",
      "description": "A supportive sports bra with breathable material.",
      "price": 29.99,
      "category": "Sportswear",
      "brandName": "FitGear",
      "rating": 4.7,
      "creationDateTime": "2024-06-28T10:20:00Z"
    },
    {
      "productName": "Compression Socks",
      "productImage": "https://i.ibb.co/ydzFR9Q/pexels-cottonbro-4569289.jpg",
      "description": "A pair of compression socks for improved circulation during workouts.",
      "price": 19.99,
      "category": "Sportswear",
      "brandName": "FitGear",
      "rating": 4.5,
      "creationDateTime": "2024-06-27T11:40:00Z"
    },
    {
      "productName": "Basketball",
      "productImage": "https://i.ibb.co/J7cqQHv/pexels-markusspiske-1752757.jpg",
      "description": "An official size and weight basketball with excellent grip.",
      "price": 29.99,
      "category": "Sportswear",
      "brandName": "FitGear",
      "rating": 4.8,
      "creationDateTime": "2024-06-26T08:30:00Z"
    },
    {
      "productName": "Resistance Bands",
      "productImage": "https://i.ibb.co/6gNG1Kf/pexels-klaus-nielsen-6303496.jpg",
      "description": "A set of resistance bands for strength training and flexibility exercises.",
      "price": 24.99,
      "category": "Sportswear",
      "brandName": "FitGear",
      "rating": 4.7,
      "creationDateTime": "2024-06-25T12:50:00Z"
    },
    {
      "productName": "Lip Balm",
      "productImage": "https://i.ibb.co/DWT6PRy/pexels-shkrabaanthony-6187571.jpg",
      "description": "A moisturizing lip balm with SPF 15 for sun protection.",
      "price": 5.99,
      "category": "Beauty and Health",
      "brandName": "WellnessPro",
      "rating": 4.6,
      "creationDateTime": "2024-06-24T09:30:00Z"
    },
    {
      "productName": "Face Cream",
      "productImage": "https://i.ibb.co/G2gJnfw/pexels-moose-photos-170195-1029896.jpg",
      "description": "A hydrating face cream with anti-aging ingredients.",
      "price": 29.99,
      "category": "Beauty and Health",
      "brandName": "WellnessPro",
      "rating": 4.7,
      "creationDateTime": "2024-06-23T10:10:00Z"
    },
    {
      "productName": "Sunscreen Lotion",
      "productImage": "https://i.ibb.co/QpL6jMF/pexels-kindelmedia-8215122.jpg",
      "description": "A broad-spectrum sunscreen lotion with SPF 50.",
      "price": 14.99,
      "category": "Beauty & Health",
      "brandName": "WellnessPro",
      "rating": 4.8,
      "creationDateTime": "2024-06-22T11:20:00Z"
    },
    {
      "productName": "Shampoo",
      "productImage": "https://i.ibb.co/GHzw240/pexels-polina-tankilevitch-3735627.jpg",
      "description": "A sulfate-free shampoo with nourishing ingredients for healthy hair.",
      "price": 12.99,
      "category": "Beauty & Health",
      "brandName": "WellnessPro",
      "rating": 4.6,
      "creationDateTime": "2024-06-21T08:40:00Z"
    },
    {
      "productName": "Conditioner",
      "productImage": "https://i.ibb.co/7Cw635Q/pexels-cottonbro-7428097.jpg",
      "description": "A moisturizing conditioner that leaves hair soft and smooth.",
      "price": 13.99,
      "category": "Beauty & Health",
      "brandName": "WellnessPro",
      "rating": 4.7,
      "creationDateTime": "2024-06-20T09:55:00Z"
    },
    {
      "productName": "Perfume",
      "productImage": "https://i.ibb.co/WK4p6n7/pexels-didsss-1190829.jpg",
      "description": "A long-lasting perfume with a floral and woody fragrance.",
      "price": 59.99,
      "category": "Beauty & Health",
      "brandName": "WellnessPro",
      "rating": 4.7,
      "creationDateTime": "2024-06-17T11:40:00Z"
    }
  ]
  